shakenfist_utilities/__init__.py
shakenfist_utilities/_version.py
shakenfist_utilities/api.py
shakenfist_utilities/logs.py
shakenfist_utilities/random.py
shakenfist_utilities/tests/__init__.py
shakenfist_utilities-0.8.4.dist-info/licenses/AUTHORS
shakenfist_utilities-0.8.4.dist-info/licenses/LICENSE
shakenfist_utilities-0.8.4.dist-info/METADATA
shakenfist_utilities-0.8.4.dist-info/WHEEL
shakenfist_utilities-0.8.4.dist-info/top_level.txt
shakenfist_utilities-0.8.4.dist-info/RECORD
